README.md
setup.py
alibabacloud_dkms_gcs.egg-info/PKG-INFO
alibabacloud_dkms_gcs.egg-info/SOURCES.txt
alibabacloud_dkms_gcs.egg-info/dependency_links.txt
alibabacloud_dkms_gcs.egg-info/requires.txt
alibabacloud_dkms_gcs.egg-info/top_level.txt
openapi/__init__.py
openapi/client.py
openapi/models.py
openapi_credential/__init__.py
openapi_credential/client.py
openapi_credential/models.py
openapi_util/__init__.py
openapi_util/client.py
openapi_util/models.py
openapi_util/protobuf/__init__.py
openapi_util/protobuf/api_pb2.py
sdk/__init__.py
sdk/client.py
sdk/models.py