Metadata-Version: 2.1
Name: alibabacloud-dkms-gcs
Version: 1.0.1
Summary: AlibabaCloud DKMS-GCS SDK for Python
Home-page: https://github.com/aliyun/alibabacloud-dkms-gcs-python-sdk
Author: Alibaba Cloud SDK
Author-email: sdk-team@alibabacloud.com
License: Apache License 2.0
Keywords: alibabacloud,dkms_gcs_sdk
Platform: any
Classifier: Development Status :: 5 - Production/Stable
Classifier: Programming Language :: Python
Classifier: Programming Language :: Python :: 3
Classifier: Programming Language :: Python :: 3.6
Classifier: Programming Language :: Python :: 3.7
Classifier: Programming Language :: Python :: 3.8
Classifier: Programming Language :: Python :: 3.9
Classifier: Programming Language :: Python :: Implementation :: CPython
Classifier: Topic :: Software Development
